README.txt
setup.cfg
setup.py
docs/HISTORY.txt
pcommerce/__init__.py
pcommerce.email.egg-info/PKG-INFO
pcommerce.email.egg-info/SOURCES.txt
pcommerce.email.egg-info/dependency_links.txt
pcommerce.email.egg-info/entry_points.txt
pcommerce.email.egg-info/namespace_packages.txt
pcommerce.email.egg-info/not-zip-safe
pcommerce.email.egg-info/requires.txt
pcommerce.email.egg-info/top_level.txt
pcommerce/email/__init__.py
pcommerce/email/configure.zcml
pcommerce/email/order.py
pcommerce/email/utility.py
pcommerce/email/browser/__init__.py
pcommerce/email/browser/configure.zcml
pcommerce/email/browser/info.py
pcommerce/email/browser/pre.py
pcommerce/email/browser/process.py
pcommerce/email/browser/images/email_icon.gif
pcommerce/email/browser/images/email_logo.gif
pcommerce/email/browser/javascripts/pcommerce.email.js
pcommerce/email/browser/stylesheets/pcommerce.email.css
pcommerce/email/browser/templates/email_form.pt
pcommerce/email/browser/templates/email_info.pt
pcommerce/email/i18n/pcommerce.email-de.po
pcommerce/email/profiles/default/componentregistry.xml
pcommerce/email/profiles/default/cssregistry.xml
pcommerce/email/profiles/default/jsregistry.xml
pcommerce/email/profiles/default/metadata.xml