Metadata-Version: 1.0
Name: pcommerce.email
Version: 0.4
Summary: UNKNOWN
Home-page: http://raptus.com
Author: Raptus AG
Author-email: skaeser@raptus.com
License: GPL
Keywords: plone ecommerce pcommerce shop payment
Platform: UNKNOWN
Classifier: Programming Language :: Python
Classifier: Topic :: Software Development :: Libraries :: Python Modules
